{
    "0":{
        "kanji":"\u611b",
        "read":[
            "\u3042\u3044"
        ]
    },
    "1":{
        "kanji":"\u6848",
        "read":[
            "\u3042\u3093"
        ]
    },
    "2":{
        "kanji":"\u4ee5",
        "read":[
            "\u3044"
        ]
    },
    "3":{
        "kanji":"\u8863",
        "read":[
            "\u3044",
            "\u3053\u308d\u3082"
        ]
    },
    "4":{
        "kanji":"\u4f4d",
        "read":[
            "\u3044",
            "\u304f\u3089\u3044"
        ]
    },
    "5":{
        "kanji":"\u56f2",
        "read":[
            "\u3044",
            "\u304b\u3053\u3080",
            "\u304b\u3053\u3046"
        ]
    },
    "6":{
        "kanji":"\u80c3",
        "read":[
            "\u3044"
        ]
    },
    "7":{
        "kanji":"\u5370",
        "read":[
            "\u3044\u3093",
            "\u3057\u308b\u3057"
        ]
    },
    "8":{
        "kanji":"\u82f1",
        "read":[
            "\u3048\u3044"
        ]
    },
    "9":{
        "kanji":"\u6804",
        "read":[
            "\u3048\u3044",
            "\u3055\u304b\u3048\u308b",
            "\u306f\u3048",
            "\u306f\u3048\u308b"
        ]
    },
    "10":{
        "kanji":"\u5869",
        "read":[
            "\u3048\u3093",
            "\u3057\u304a"
        ]
    },
    "11":{
        "kanji":"\u5104",
        "read":[
            "\u304a\u304f"
        ]
    },
    "12":{
        "kanji":"\u52a0",
        "read":[
            "\u304b",
            "\u304f\u308f\u3048\u308b",
            "\u304f\u308f\u308f\u308b"
        ]
    },
    "13":{
        "kanji":"\u679c",
        "read":[
            "\u304b",
            "\u306f\u305f\u3059",
            "\u306f\u3066\u308b",
            "\u306f\u3066"
        ]
    },
    "14":{
        "kanji":"\u8ca8",
        "read":[
            "\u304b"
        ]
    },
    "15":{
        "kanji":"\u8ab2",
        "read":[
            "\u304b"
        ]
    },
    "16":{
        "kanji":"\u82bd",
        "read":[
            "\u304c",
            "\u3081"
        ]
    },
    "17":{
        "kanji":"\u6539",
        "read":[
            "\u304b\u3044",
            "\u3042\u3089\u305f\u3081\u308b",
            "\u3042\u3089\u305f\u307e\u308b"
        ]
    },
    "18":{
        "kanji":"\u68b0",
        "read":[
            "\u304b\u3044"
        ]
    },
    "19":{
        "kanji":"\u5bb3",
        "read":[
            "\u304c\u3044"
        ]
    },
    "20":{
        "kanji":"\u8857",
        "read":[
            "\u304c\u3044",
            "\u304b\u3044",
            "\u307e\u3061"
        ]
    },
    "21":{
        "kanji":"\u5404",
        "read":[
            "\u304b\u304f",
            "\u304a\u306e\u304a\u306e"
        ]
    },
    "22":{
        "kanji":"\u899a",
        "read":[
            "\u304b\u304f",
            "\u304a\u307c\u3048\u308b",
            "\u3055\u307e\u3059",
            "\u3055\u3081\u308b"
        ]
    },
    "23":{
        "kanji":"\u5b8c",
        "read":[
            "\u304b\u3093"
        ]
    },
    "24":{
        "kanji":"\u5b98",
        "read":[
            "\u304b\u3093"
        ]
    },
    "25":{
        "kanji":"\u7ba1",
        "read":[
            "\u304b\u3093",
            "\u304f\u3060"
        ]
    },
    "26":{
        "kanji":"\u95a2",
        "read":[
            "\u304b\u3093",
            "\u305b\u304d",
            "\u304b\u304b\u308f\u308b"
        ]
    },
    "27":{
        "kanji":"\u89b3",
        "read":[
            "\u304b\u3093"
        ]
    },
    "28":{
        "kanji":"\u9858",
        "read":[
            "\u304c\u3093",
            "\u306d\u304c\u3046"
        ]
    },
    "29":{
        "kanji":"\u5e0c",
        "read":[
            "\u304d"
        ]
    },
    "30":{
        "kanji":"\u5b63",
        "read":[
            "\u304d"
        ]
    },
    "31":{
        "kanji":"\u7d00",
        "read":[
            "\u304d"
        ]
    },
    "32":{
        "kanji":"\u559c",
        "read":[
            "\u304d",
            "\u3088\u308d\u3053\u3076"
        ]
    },
    "33":{
        "kanji":"\u65d7",
        "read":[
            "\u304d",
            "\u306f\u305f"
        ]
    },
    "34":{
        "kanji":"\u5668",
        "read":[
            "\u304d",
            "\u3046\u3064\u308f"
        ]
    },
    "35":{
        "kanji":"\u6a5f",
        "read":[
            "\u304d",
            "\u306f\u305f"
        ]
    },
    "36":{
        "kanji":"\u8b70",
        "read":[
            "\u304e"
        ]
    },
    "37":{
        "kanji":"\u6c42",
        "read":[
            "\u304d\u3085\u3046",
            "\u3082\u3068\u3081\u308b"
        ]
    },
    "38":{
        "kanji":"\u6ce3",
        "read":[
            "\u304d\u3085\u3046",
            "\u306a\u304f"
        ]
    },
    "39":{
        "kanji":"\u6551",
        "read":[
            "\u304d\u3085\u3046",
            "\u3059\u304f\u3046"
        ]
    },
    "40":{
        "kanji":"\u7d66",
        "read":[
            "\u304d\u3085\u3046"
        ]
    },
    "41":{
        "kanji":"\u6319",
        "read":[
            "\u304d\u3087",
            "\u3042\u3052\u308b",
            "\u3042\u304c\u308b"
        ]
    },
    "42":{
        "kanji":"\u6f01",
        "read":[
            "\u304e\u3087",
            "\u308a\u3087\u3046"
        ]
    },
    "43":{
        "kanji":"\u5171",
        "read":[
            "\u304d\u3087\u3046",
            "\u3068\u3082"
        ]
    },
    "44":{
        "kanji":"\u5354",
        "read":[
            "\u304d\u3087\u3046"
        ]
    },
    "45":{
        "kanji":"\u93e1",
        "read":[
            "\u304d\u3087\u3046",
            "\u304b\u304c\u307f"
        ]
    },
    "46":{
        "kanji":"\u7af6",
        "read":[
            "\u304d\u3087\u3046",
            "\u3051\u3044",
            "\u304d\u305d\u3046",
            "\u305b\u308b"
        ]
    },
    "47":{
        "kanji":"\u6975",
        "read":[
            "\u304d\u3087\u304f",
            "\u3054\u304f",
            "\u304d\u308f\u3081\u308b",
            "\u304d\u308f\u307e\u308b",
            "\u304d\u308f\u307f"
        ]
    },
    "48":{
        "kanji":"\u8a13",
        "read":[
            "\u304f\u3093"
        ]
    },
    "49":{
        "kanji":"\u8ecd",
        "read":[
            "\u3050\u3093"
        ]
    },
    "50":{
        "kanji":"\u90e1",
        "read":[
            "\u3050\u3093"
        ]
    },
    "51":{
        "kanji":"\u5f84",
        "read":[
            "\u3051\u3044"
        ]
    },
    "52":{
        "kanji":"\u578b",
        "read":[
            "\u3051\u3044",
            "\u304b\u305f"
        ]
    },
    "53":{
        "kanji":"\u666f",
        "read":[
            "\u3051\u3044"
        ]
    },
    "54":{
        "kanji":"\u82b8",
        "read":[
            "\u3052\u3044"
        ]
    },
    "55":{
        "kanji":"\u6b20",
        "read":[
            "\u3051\u3064",
            "\u304b\u3051\u308b",
            "\u304b\u304f"
        ]
    },
    "56":{
        "kanji":"\u7d50",
        "read":[
            "\u3051\u3064",
            "\u3080\u3059\u3076",
            "\u3086\u3046",
            "\u3086\u308f\u3048\u308b"
        ]
    },
    "57":{
        "kanji":"\u5efa",
        "read":[
            "\u3051\u3093",
            "\u3053\u3093",
            "\u305f\u3066\u308b",
            "\u305f\u3064"
        ]
    },
    "58":{
        "kanji":"\u5065",
        "read":[
            "\u3051\u3093",
            "\u3059\u3053\u3084\u304b"
        ]
    },
    "59":{
        "kanji":"\u9a13",
        "read":[
            "\u3051\u3093",
            "\u3052\u3093"
        ]
    },
    "60":{
        "kanji":"\u56fa",
        "read":[
            "\u3053",
            "\u304b\u305f\u3081\u308b",
            "\u304b\u305f\u307e\u308b",
            "\u304b\u305f\u3044"
        ]
    },
    "61":{
        "kanji":"\u529f",
        "read":[
            "\u3053\u3046",
            "\u304f"
        ]
    },
    "62":{
        "kanji":"\u597d",
        "read":[
            "\u3053\u3046",
            "\u3053\u306e\u3080",
            "\u3059\u304f"
        ]
    },
    "63":{
        "kanji":"\u5019",
        "read":[
            "\u3053\u3046",
            "\u305d\u3046\u308d\u3046"
        ]
    },
    "64":{
        "kanji":"\u822a",
        "read":[
            "\u3053\u3046"
        ]
    },
    "65":{
        "kanji":"\u5eb7",
        "read":[
            "\u3053\u3046"
        ]
    },
    "66":{
        "kanji":"\u544a",
        "read":[
            "\u3053\u304f",
            "\u3064\u3052\u308b"
        ]
    },
    "67":{
        "kanji":"\u5dee",
        "read":[
            "\u3055",
            "\u3055\u3059"
        ]
    },
    "68":{
        "kanji":"\u83dc",
        "read":[
            "\u3055\u3044",
            "\u306a"
        ]
    },
    "69":{
        "kanji":"\u6700",
        "read":[
            "\u3055\u3044",
            "\u3082\u3063\u3068\u3082"
        ]
    },
    "70":{
        "kanji":"\u6750",
        "read":[
            "\u3056\u3044"
        ]
    },
    "71":{
        "kanji":"\u6628",
        "read":[
            "\u3055\u304f"
        ]
    },
    "72":{
        "kanji":"\u672d",
        "read":[
            "\u3055\u3064",
            "\u3075\u3060"
        ]
    },
    "73":{
        "kanji":"\u5237",
        "read":[
            "\u3055\u3064",
            "\u3059\u308b"
        ]
    },
    "74":{
        "kanji":"\u6bba",
        "read":[
            "\u3055\u3064",
            "\u3055\u3044",
            "\u305b\u3064",
            "\u3053\u308d\u3059"
        ]
    },
    "75":{
        "kanji":"\u5bdf",
        "read":[
            "\u3055\u3064"
        ]
    },
    "76":{
        "kanji":"\u53c2",
        "read":[
            "\u3055\u3093",
            "\u307e\u3044\u308b"
        ]
    },
    "77":{
        "kanji":"\u7523",
        "read":[
            "\u3055\u3093",
            "\u3046\u3080",
            "\u3046\u307e\u308c\u308b",
            "\u3046\u3076"
        ]
    },
    "78":{
        "kanji":"\u6563",
        "read":[
            "\u3055\u3093",
            "\u3061\u308b",
            "\u3061\u3089\u3059",
            "\u3061\u3089\u304b\u3059",
            "\u3061\u3089\u304b\u308b"
        ]
    },
    "79":{
        "kanji":"\u6b8b",
        "read":[
            "\u3056\u3093",
            "\u306e\u3053\u308b",
            "\u306e\u3053\u3059"
        ]
    },
    "80":{
        "kanji":"\u58eb",
        "read":[
            "\u3057"
        ]
    },
    "81":{
        "kanji":"\u6c0f",
        "read":[
            "\u3057",
            "\u3046\u3058"
        ]
    },
    "82":{
        "kanji":"\u53f2",
        "read":[
            "\u3057"
        ]
    },
    "83":{
        "kanji":"\u53f8",
        "read":[
            "\u3057"
        ]
    },
    "84":{
        "kanji":"\u8a66",
        "read":[
            "\u3057",
            "\u3053\u3053\u308d\u307f\u308b",
            "\u305f\u3081\u3059"
        ]
    },
    "85":{
        "kanji":"\u5150",
        "read":[
            "\u3058",
            "\u306b"
        ]
    },
    "86":{
        "kanji":"\u6cbb",
        "read":[
            "\u3058",
            "\u3061",
            "\u304a\u3055\u3081\u308b",
            "\u304a\u3055\u307e\u308b",
            "\u306a\u304a\u308b",
            "\u306a\u304a\u3059"
        ]
    },
    "87":{
        "kanji":"\u8f9e",
        "read":[
            "\u3058",
            "\u3084\u3081\u308b"
        ]
    },
    "88":{
        "kanji":"\u5931",
        "read":[
            "\u3057\u3064",
            "\u3046\u3057\u306a\u3046"
        ]
    },
    "89":{
        "kanji":"\u501f",
        "read":[
            "\u3057\u3083\u304f",
            "\u304b\u308a\u308b"
        ]
    },
    "90":{
        "kanji":"\u7a2e",
        "read":[
            "\u3057\u3085",
            "\u305f\u306d"
        ]
    },
    "91":{
        "kanji":"\u5468",
        "read":[
            "\u3057\u3085\u3046",
            "\u307e\u308f\u308a"
        ]
    },
    "92":{
        "kanji":"\u795d",
        "read":[
            "\u3057\u3085\u304f",
            "\u3057\u3085\u3046",
            "\u3044\u308f\u3046"
        ]
    },
    "93":{
        "kanji":"\u9806",
        "read":[
            "\u3058\u3085\u3093"
        ]
    },
    "94":{
        "kanji":"\u521d",
        "read":[
            "\u3057\u3087",
            "\u306f\u3058\u3081",
            "\u306f\u3058\u3081\u3066",
            "\u306f\u3064",
            "\u3046\u3044",
            "\u305d\u3081\u308b"
        ]
    },
    "95":{
        "kanji":"\u677e",
        "read":[
            "\u3057\u3087\u3046",
            "\u307e\u3064"
        ]
    },
    "96":{
        "kanji":"\u7b11",
        "read":[
            "\u3057\u3087\u3046",
            "\u308f\u3089\u3046",
            "\u3048\u3080"
        ]
    },
    "97":{
        "kanji":"\u5531",
        "read":[
            "\u3057\u3087\u3046",
            "\u3068\u306a\u3048\u308b"
        ]
    },
    "98":{
        "kanji":"\u713c",
        "read":[
            "\u3057\u3087\u3046",
            "\u3084\u304f",
            "\u3084\u3051\u308b"
        ]
    },
    "99":{
        "kanji":"\u8c61",
        "read":[
            "\u3057\u3087\u3046",
            "\u305e\u3046"
        ]
    },
    "100":{
        "kanji":"\u7167",
        "read":[
            "\u3057\u3087\u3046",
            "\u3066\u308b",
            "\u3066\u3089\u3059",
            "\u3066\u308c\u308b"
        ]
    },
    "101":{
        "kanji":"\u8cde",
        "read":[
            "\u3057\u3087\u3046"
        ]
    },
    "102":{
        "kanji":"\u81e3",
        "read":[
            "\u3057\u3093",
            "\u3058\u3093"
        ]
    },
    "103":{
        "kanji":"\u4fe1",
        "read":[
            "\u3057\u3093"
        ]
    },
    "104":{
        "kanji":"\u6210",
        "read":[
            "\u305b\u3044",
            "\u3058\u3087\u3046",
            "\u306a\u308b",
            "\u306a\u3059"
        ]
    },
    "105":{
        "kanji":"\u7701",
        "read":[
            "\u305b\u3044",
            "\u3057\u3087\u3046",
            "\u304b\u3048\u308a\u307f\u308b",
            "\u306f\u3076\u304f"
        ]
    },
    "106":{
        "kanji":"\u6e05",
        "read":[
            "\u305b\u3044",
            "\u3057\u3087\u3046",
            "\u304d\u3088\u3044",
            "\u304d\u3088\u307e\u308b",
            "\u304d\u3088\u3081\u308b"
        ]
    },
    "107":{
        "kanji":"\u9759",
        "read":[
            "\u305b\u3044",
            "\u3058\u3087\u3046",
            "\u3057\u305a",
            "\u3057\u305a\u304b",
            "\u3057\u305a\u307e\u308b",
            "\u3057\u305a\u3081\u308b"
        ]
    },
    "108":{
        "kanji":"\u5e2d",
        "read":[
            "\u305b\u304d"
        ]
    },
    "109":{
        "kanji":"\u7a4d",
        "read":[
            "\u305b\u304d",
            "\u3064\u3080",
            "\u3064\u3082\u308b"
        ]
    },
    "110":{
        "kanji":"\u6298",
        "read":[
            "\u305b\u3064",
            "\u304a\u308b",
            "\u304a\u308a",
            "\u304a\u308c\u308b"
        ]
    },
    "111":{
        "kanji":"\u7bc0",
        "read":[
            "\u305b\u3064",
            "\u305b\u3061",
            "\u3075\u3057"
        ]
    },
    "112":{
        "kanji":"\u8aac",
        "read":[
            "\u305b\u3064",
            "\u305c\u3044",
            "\u3068\u304f"
        ]
    },
    "113":{
        "kanji":"\u6d45",
        "read":[
            "\u305b\u3093",
            "\u3042\u3055\u3044"
        ]
    },
    "114":{
        "kanji":"\u6226",
        "read":[
            "\u305b\u3093",
            "\u3044\u304f\u3055",
            "\u305f\u305f\u304b\u3046"
        ]
    },
    "115":{
        "kanji":"\u9078",
        "read":[
            "\u305b\u3093",
            "\u3048\u3089\u3076"
        ]
    },
    "116":{
        "kanji":"\u7136",
        "read":[
            "\u305c\u3093",
            "\u306d\u3093"
        ]
    },
    "117":{
        "kanji":"\u4e89",
        "read":[
            "\u305d\u3046",
            "\u3042\u3089\u305d\u3046"
        ]
    },
    "118":{
        "kanji":"\u5009",
        "read":[
            "\u305d\u3046",
            "\u304f\u3089"
        ]
    },
    "119":{
        "kanji":"\u5de3",
        "read":[
            "\u305d\u3046",
            "\u3059"
        ]
    },
    "120":{
        "kanji":"\u675f",
        "read":[
            "\u305d\u304f",
            "\u305f\u3070"
        ]
    },
    "121":{
        "kanji":"\u5074",
        "read":[
            "\u305d\u304f",
            "\u304c\u308f"
        ]
    },
    "122":{
        "kanji":"\u7d9a",
        "read":[
            "\u305e\u304f",
            "\u3064\u3065\u304f",
            "\u3064\u3065\u3051\u308b"
        ]
    },
    "123":{
        "kanji":"\u5352",
        "read":[
            "\u305d\u3064"
        ]
    },
    "124":{
        "kanji":"\u5b6b",
        "read":[
            "\u305d\u3093",
            "\u307e\u3054"
        ]
    },
    "125":{
        "kanji":"\u5e2f",
        "read":[
            "\u305f\u3044",
            "\u304a\u3073\u308b",
            "\u304a\u3073"
        ]
    },
    "126":{
        "kanji":"\u968a",
        "read":[
            "\u305f\u3044"
        ]
    },
    "127":{
        "kanji":"\u9054",
        "read":[
            "\u305f\u3064"
        ]
    },
    "128":{
        "kanji":"\u5358",
        "read":[
            "\u305f\u3093"
        ]
    },
    "129":{
        "kanji":"\u7f6e",
        "read":[
            "\u3061",
            "\u304a\u304f"
        ]
    },
    "130":{
        "kanji":"\u4ef2",
        "read":[
            "\u3061\u3085\u3046",
            "\u306a\u304b"
        ]
    },
    "131":{
        "kanji":"\u8caf",
        "read":[
            "\u3061\u3087"
        ]
    },
    "132":{
        "kanji":"\u5146",
        "read":[
            "\u3061\u3087\u3046",
            "\u304d\u3056\u3059",
            "\u304d\u3056\u3057"
        ]
    },
    "133":{
        "kanji":"\u8178",
        "read":[
            "\u3061\u3087\u3046"
        ]
    },
    "134":{
        "kanji":"\u4f4e",
        "read":[
            "\u3066\u3044",
            "\u3072\u304f\u3044",
            "\u3072\u304f\u3081\u308b",
            "\u3072\u304f\u307e\u308b"
        ]
    },
    "135":{
        "kanji":"\u5e95",
        "read":[
            "\u3066\u3044",
            "\u305d\u3053"
        ]
    },
    "136":{
        "kanji":"\u505c",
        "read":[
            "\u3066\u3044"
        ]
    },
    "137":{
        "kanji":"\u7684",
        "read":[
            "\u3066\u304d",
            "\u307e\u3068"
        ]
    },
    "138":{
        "kanji":"\u5178",
        "read":[
            "\u3066\u3093"
        ]
    },
    "139":{
        "kanji":"\u4f1d",
        "read":[
            "\u3067\u3093",
            "\u3064\u305f\u308f\u308b",
            "\u3064\u305f\u3048\u308b",
            "\u3064\u305f\u3046"
        ]
    },
    "140":{
        "kanji":"\u5f92",
        "read":[
            "\u3068"
        ]
    },
    "141":{
        "kanji":"\u52aa",
        "read":[
            "\u3069",
            "\u3064\u3068\u3081\u308b"
        ]
    },
    "142":{
        "kanji":"\u706f",
        "read":[
            "\u3068\u3046",
            "\u3072"
        ]
    },
    "143":{
        "kanji":"\u5802",
        "read":[
            "\u3069\u3046"
        ]
    },
    "144":{
        "kanji":"\u50cd",
        "read":[
            "\u3069\u3046",
            "\u306f\u305f\u3089\u304f"
        ]
    },
    "145":{
        "kanji":"\u7279",
        "read":[
            "\u3068\u304f"
        ]
    },
    "146":{
        "kanji":"\u5f97",
        "read":[
            "\u3068\u304f",
            "\u3048\u308b",
            "\u3046\u308b"
        ]
    },
    "147":{
        "kanji":"\u6bd2",
        "read":[
            "\u3069\u304f"
        ]
    },
    "148":{
        "kanji":"\u71b1",
        "read":[
            "\u306d\u3064",
            "\u3042\u3064\u3044"
        ]
    },
    "149":{
        "kanji":"\u5ff5",
        "read":[
            "\u306d\u3093"
        ]
    },
    "150":{
        "kanji":"\u6557",
        "read":[
            "\u306f\u3044",
            "\u3084\u3076\u308c\u308b"
        ]
    },
    "151":{
        "kanji":"\u6885",
        "read":[
            "\u3070\u3044",
            "\u3046\u3081"
        ]
    },
    "152":{
        "kanji":"\u535a",
        "read":[
            "\u306f\u304f",
            "\u3070\u304f"
        ]
    },
    "153":{
        "kanji":"\u98ef",
        "read":[
            "\u306f\u3093",
            "\u3081\u3057"
        ]
    },
    "154":{
        "kanji":"\u98db",
        "read":[
            "\u3072",
            "\u3068\u3076",
            "\u3068\u3070\u3059"
        ]
    },
    "155":{
        "kanji":"\u8cbb",
        "read":[
            "\u3072",
            "\u3064\u3044\u3084\u3059",
            "\u3064\u3044\u3048\u308b"
        ]
    },
    "156":{
        "kanji":"\u5fc5",
        "read":[
            "\u3072\u3064",
            "\u304b\u306a\u3089\u305a"
        ]
    },
    "157":{
        "kanji":"\u7968",
        "read":[
            "\u3072\u3087\u3046"
        ]
    },
    "158":{
        "kanji":"\u6a19",
        "read":[
            "\u3072\u3087\u3046"
        ]
    },
    "159":{
        "kanji":"\u4e0d",
        "read":[
            "\u3075",
            "\u3076"
        ]
    },
    "160":{
        "kanji":"\u592b",
        "read":[
            "\u3075",
            "\u3075\u3046",
            "\u304a\u3063\u3068"
        ]
    },
    "161":{
        "kanji":"\u4ed8",
        "read":[
            "\u3075",
            "\u3064\u3051\u308b",
            "\u3064\u304f"
        ]
    },
    "162":{
        "kanji":"\u5e9c",
        "read":[
            "\u3075"
        ]
    },
    "163":{
        "kanji":"\u526f",
        "read":[
            "\u3075\u304f"
        ]
    },
    "164":{
        "kanji":"\u7c89",
        "read":[
            "\u3075\u3093",
            "\u3053",
            "\u3053\u306a"
        ]
    },
    "165":{
        "kanji":"\u5175",
        "read":[
            "\u3078\u3044",
            "\u3072\u3087\u3046"
        ]
    },
    "166":{
        "kanji":"\u5225",
        "read":[
            "\u3079\u3064",
            "\u308f\u304b\u308c\u308b"
        ]
    },
    "167":{
        "kanji":"\u8fba",
        "read":[
            "\u3078\u3093",
            "\u3042\u305f\u308a",
            "\u3079"
        ]
    },
    "168":{
        "kanji":"\u5909",
        "read":[
            "\u3078\u3093",
            "\u304b\u308f\u308b",
            "\u304b\u3048\u308b"
        ]
    },
    "169":{
        "kanji":"\u4fbf",
        "read":[
            "\u3079\u3093",
            "\u3073\u3093",
            "\u305f\u3088\u308a"
        ]
    },
    "170":{
        "kanji":"\u5305",
        "read":[
            "\u307b\u3046",
            "\u3064\u3064\u3080"
        ]
    },
    "171":{
        "kanji":"\u6cd5",
        "read":[
            "\u307b\u3046",
            "\u306f\u3063",
            "\u307b\u3063"
        ]
    },
    "172":{
        "kanji":"\u671b",
        "read":[
            "\u307c\u3046",
            "\u3082\u3046",
            "\u306e\u305e\u3080"
        ]
    },
    "173":{
        "kanji":"\u7267",
        "read":[
            "\u307c\u304f",
            "\u307e\u304d"
        ]
    },
    "174":{
        "kanji":"\u672b",
        "read":[
            "\u307e\u3064",
            "\u3070\u3064",
            "\u3059\u3048"
        ]
    },
    "175":{
        "kanji":"\u6e80",
        "read":[
            "\u307e\u3093",
            "\u307f\u3061\u308b",
            "\u307f\u305f\u3059"
        ]
    },
    "176":{
        "kanji":"\u672a",
        "read":[
            "\u307f"
        ]
    },
    "177":{
        "kanji":"\u8108",
        "read":[
            "\u307f\u3083\u304f"
        ]
    },
    "178":{
        "kanji":"\u6c11",
        "read":[
            "\u307f\u3093",
            "\u305f\u307f"
        ]
    },
    "179":{
        "kanji":"\u7121",
        "read":[
            "\u3080",
            "\u3076",
            "\u306a\u3044"
        ]
    },
    "180":{
        "kanji":"\u7d04",
        "read":[
            "\u3084\u304f"
        ]
    },
    "181":{
        "kanji":"\u52c7",
        "read":[
            "\u3086\u3046",
            "\u3044\u3055\u3080"
        ]
    },
    "182":{
        "kanji":"\u8981",
        "read":[
            "\u3088\u3046",
            "\u304b\u306a\u3081",
            "\u3044\u308b"
        ]
    },
    "183":{
        "kanji":"\u990a",
        "read":[
            "\u3088\u3046",
            "\u3084\u3057\u306a\u3046"
        ]
    },
    "184":{
        "kanji":"\u6d74",
        "read":[
            "\u3088\u304f",
            "\u3042\u3073\u308b",
            "\u3042\u3073\u305b\u308b"
        ]
    },
    "185":{
        "kanji":"\u5229",
        "read":[
            "\u308a",
            "\u304d\u304f"
        ]
    },
    "186":{
        "kanji":"\u9678",
        "read":[
            "\u308a\u304f"
        ]
    },
    "187":{
        "kanji":"\u826f",
        "read":[
            "\u308a\u3087\u3046",
            "\u3088\u3044"
        ]
    },
    "188":{
        "kanji":"\u6599",
        "read":[
            "\u308a\u3087\u3046"
        ]
    },
    "189":{
        "kanji":"\u91cf",
        "read":[
            "\u308a\u3087\u3046",
            "\u306f\u304b\u308b"
        ]
    },
    "190":{
        "kanji":"\u8f2a",
        "read":[
            "\u308a\u3093",
            "\u308f"
        ]
    },
    "191":{
        "kanji":"\u985e",
        "read":[
            "\u308b\u3044",
            "\u305f\u3050\u3044"
        ]
    },
    "192":{
        "kanji":"\u4ee4",
        "read":[
            "\u308c\u3044"
        ]
    },
    "193":{
        "kanji":"\u51b7",
        "read":[
            "\u308c\u3044",
            "\u3064\u3081\u305f\u3044",
            "\u3072\u3048\u308b",
            "\u3072\u3084",
            "\u3072\u3084\u3059",
            "\u3072\u3084\u304b\u3059",
            "\u3055\u3081\u308b",
            "\u3055\u307e\u3059"
        ]
    },
    "194":{
        "kanji":"\u4f8b",
        "read":[
            "\u308c\u3044",
            "\u305f\u3068\u3048\u308b"
        ]
    },
    "195":{
        "kanji":"\u6b74",
        "read":[
            "\u308c\u304d"
        ]
    },
    "196":{
        "kanji":"\u9023",
        "read":[
            "\u308c\u3093",
            "\u3064\u3089\u306a\u308b",
            "\u3064\u3089\u306d\u308b",
            "\u3064\u308c\u308b"
        ]
    },
    "197":{
        "kanji":"\u8001",
        "read":[
            "\u308d\u3046",
            "\u304a\u3044\u308b",
            "\u3075\u3051\u308b"
        ]
    },
    "198":{
        "kanji":"\u52b4",
        "read":[
            "\u308d\u3046"
        ]
    },
    "199":{
        "kanji":"\u9332",
        "read":[
            "\u308d\u304f"
        ]
    }
}